{
	"schemaVersion": 1,
	"id": "minedog-mod",
	"version": "${version}",
	"name": "MineDog Mod",
	"description": "This is an MineDog mod;",
	"authors": [
		"Me!"
	],
	"contact": {
		"homepage": "https://fabricmc.net/",
		"sources": "https://github.com/FabricMC/fabric-example-mod"
	},
	"license": "CC0-1.0",
	"icon": "assets/minedog-mod/icon.png",
	"environment": "*",
	"entrypoints": {
		"main": [
			"net.rainneon.minedog.MineDogMod"
		],
		"client": [
			"net.rainneon.minedog.MineDogModClient"
		],
		"fabric-datagen": [
			"net.rainneon.minedog.MineDogModDataGenerator"
		]
	},
	"mixins": [
		"minedog-mod.mixins.json"
	],
	"depends": {
		"fabricloader": ">=0.14.21",
		"minecraft": "~1.20.1",
		"java": ">=17",
		"fabric-api": "*"
	},
	"suggests": {
		"another-mod": "*"
	}
}